osw_confidence_metric/__init__.py
osw_confidence_metric/area_analyzer.py
osw_confidence_metric/osm_data_handler.py
osw_confidence_metric/trust_score_calculator.py
osw_confidence_metric/utils.py
osw_confidence_metric/version.py
osw_confidence_metric-0.0.8.dist-info/LICENSE
osw_confidence_metric-0.0.8.dist-info/METADATA
osw_confidence_metric-0.0.8.dist-info/WHEEL
osw_confidence_metric-0.0.8.dist-info/top_level.txt
osw_confidence_metric-0.0.8.dist-info/RECORD
