Metadata-Version: 2.1
Name: osw-confidence-metric
Version: 0.0.8
Summary: Calculates the confidence score of a given geojson area
Home-page: https://github.com/TaskarCenterAtUW/TDEI-python-lib-confidence-metric
Author: Sujata Misra
Author-email: sujatam@gaussiansolutions.com
Project-URL: Documentation, https://github.com/TaskarCenterAtUW/TDEI-python-lib-confidence-metric/blob/main/README.md
Project-URL: GitHub, https://github.com/TaskarCenterAtUW/TDEI-python-lib-confidence-metric
Project-URL: Changelog, https://github.com/TaskarCenterAtUW/TDEI-python-lib-confidence-metric/blob/main/CHANGELOG.md
Classifier: Programming Language :: Python :: 3
Classifier: License :: OSI Approved :: MIT License
Classifier: Operating System :: OS Independent
Requires-Python: >=3.9
License-File: LICENSE
Requires-Dist: osmapi==4.0.0
Requires-Dist: geopandas==0.14.4
Requires-Dist: osmnx==1.8.0
Requires-Dist: dask-geopandas==0.3.1
Requires-Dist: geonetworkx==0.5.3
Requires-Dist: shapely==2.0.2
Requires-Dist: coverage~=7.5.1
Requires-Dist: numpy<2.0
